pydisagg/__init__.py
pydisagg/disaggregate.py
pydisagg/transformations.py
pydisagg/typing.py
pydisagg/ihme/__init__.py
pydisagg/ihme/schema.py
pydisagg/ihme/validator.py
pydisagg/ihme/splitter/__init__.py
pydisagg/ihme/splitter/age_splitter.py
pydisagg/ihme/splitter/cat_splitter.py
pydisagg/ihme/splitter/sex_splitter.py
pydisagg/models/__init__.py
pydisagg/models/disagg_model.py
pydisagg/models/lmo_model.py
pydisagg/models/log_odds_model.py
pydisagg/models/rate_multiplicative_model.py
pydisagg-0.6.2.dist-info/licenses/LICENSE
pydisagg-0.6.2.dist-info/METADATA
pydisagg-0.6.2.dist-info/WHEEL
pydisagg-0.6.2.dist-info/top_level.txt
pydisagg-0.6.2.dist-info/RECORD
